tests/__init__.py
tests/test_cli.py
tests/test_command_handler.py
tests/test_config_manager.py
tests/test_pane_handler.py
tests/test_session_handler.py
tests/test_tmux_wrapper.py
txm/__init__.py
txm/cli.py
txm/config_manager.py
txm/tmux_wrapper.py
txm/txm_core.py
txm/action_handlers/__init__.py
txm/action_handlers/command_handler.py
txm/action_handlers/pane_handler.py
txm/action_handlers/session_handler.py
txm-0.1.0.dist-info/LICENSE
txm-0.1.0.dist-info/METADATA
txm-0.1.0.dist-info/WHEEL
txm-0.1.0.dist-info/top_level.txt
txm-0.1.0.dist-info/RECORD
