Metadata-Version: 2.1
Name: txm
Version: 0.1.0
Summary: A CLI utility for tmux
Home-page: https://github.com/MohamedElashri/txm
Author: Mohamed Elashri
Author-email: Mohamed Elashri <txm@elashri.com>
License: GPL-3.0
Project-URL: Homepage, https://github.com/MohamedElashri/txm
Project-URL: Bug Tracker, https://github.com/MohamedElashri/txm/issues
Keywords: tmux,cli,utility,terminal,multiplexer,terminal multiplexer,terminal multiplexing
Classifier: Programming Language :: Python :: 3
Classifier: Programming Language :: Python :: 3.6
Classifier: Programming Language :: Python :: 3.7
Classifier: Programming Language :: Python :: 3.8
Classifier: Programming Language :: Python :: 3.9
License-File: LICENSE
Requires-Dist: Click
